unsplash_downloader/__init__.py
unsplash_downloader/unsplash.py
unsplash_lib-0.0.3.dist-info/LICENSE
unsplash_lib-0.0.3.dist-info/METADATA
unsplash_lib-0.0.3.dist-info/WHEEL
unsplash_lib-0.0.3.dist-info/top_level.txt
unsplash_lib-0.0.3.dist-info/RECORD
