Metadata-Version: 2.1
Name: unsplash_lib
Version: 0.0.3
Summary: A python library that can download from Unsplash and also manage user account
Home-page: https://github.com/beh185/unsplash_lib
Author: Behnam
Author-email: Behii@tutanota.com
License: MIT
Keywords: download from Unsplash
Classifier: Programming Language :: Python :: 3
Classifier: Operating System :: OS Independent
Requires-Python: ~=3.7
License-File: LICENSE
Requires-Dist: requests
Requires-Dist: tqdm
